{
    "readme": "none",
    "name": "Mimbl Reference",
	"excludeExternals": true,
    "excludeInternal": true,
    "excludePrivate": true,
    "disableSources": true,
    "hideGenerator": true,
    "includeVersion": true,
	"out": "./src/web/reference",
    "entryPointStrategy": "expand",
	"entryPoints": [
		"./src/api/"
	],
    "externalSymbolLinkMappings": {
        "mimcss": {
            "WritingMode_StyleType": "https://www.mimcss.com/reference/modules/StyleTypes.html#WritingMode_StyleType",
            "*": "https://www.mimcss.com/typedoc.html"
        }
    }
}